transformers_interpret/.DS_Store
transformers_interpret/__init__.py
transformers_interpret/attributions.py
transformers_interpret/errors.py
transformers_interpret/explainer.py
transformers_interpret/explainers/text/__init__.py
transformers_interpret/explainers/text/multilabel_classification.py
transformers_interpret/explainers/text/question_answering.py
transformers_interpret/explainers/text/sequence_classification.py
transformers_interpret/explainers/text/token_classification.py
transformers_interpret/explainers/text/zero_shot_classification.py
transformers_interpret/explainers/vision/attribution_types.py
transformers_interpret/explainers/vision/image_classification.py
transformers_interpret-0.10.0.dist-info/LICENSE
transformers_interpret-0.10.0.dist-info/WHEEL
transformers_interpret-0.10.0.dist-info/METADATA
transformers_interpret-0.10.0.dist-info/RECORD
