Metadata-Version: 2.1
Name: transformers-interpret
Version: 0.10.0
Summary: Model explainability that works seamlessly with 🤗 transformers. Explain your transformers model in just 2 lines of code.
Author: Charles Pierse
Author-email: charlespierse@gmail.com
Requires-Python: >=3.7,<4.0
Classifier: Development Status :: 3 - Alpha
Classifier: Intended Audience :: Developers
Classifier: Programming Language :: Python :: 3
Classifier: Programming Language :: Python :: 3 :: Only
Classifier: Programming Language :: Python :: 3.10
Classifier: Programming Language :: Python :: 3.6
Classifier: Programming Language :: Python :: 3.7
Classifier: Programming Language :: Python :: 3.8
Classifier: Programming Language :: Python :: 3.9
Classifier: Topic :: Scientific/Engineering :: Artificial Intelligence
Classifier: Topic :: Scientific/Engineering :: Information Analysis
Classifier: Topic :: Software Development :: Libraries :: Python Modules
Classifier: Topic :: Text Processing :: Linguistic
Requires-Dist: captum (>=0.3.1)
Requires-Dist: ipython (>=7.31.1,<8.0.0)
Requires-Dist: transformers (>=3.0.0)
